{
  "group_id": "p3-narrow-rsvp-event-001",
  "group_type": "triple",
  "horizons": [
    "compact",
    "standard",
    "hard"
  ],
  "spine_source": "hand",
  "implicit_drift_type": null,
  "accepted": true,
  "rule_version": "v1.0-2026-04-26",
  "evidence_prompt_version": "v1.0-2026-04-26",
  "members": [
    {
      "horizon": "compact",
      "accepted": true,
      "failure_reason": null,
      "realize_attempts": 1,
      "evidence_attempts": 0,
      "elapsed_s": 20.58027701699757,
      "sample_id": "p3-narrow-rsvp-event-001-compact"
    },
    {
      "horizon": "standard",
      "accepted": true,
      "failure_reason": null,
      "realize_attempts": 1,
      "evidence_attempts": 0,
      "elapsed_s": 14.283471878006821,
      "sample_id": "p3-narrow-rsvp-event-001-standard"
    },
    {
      "horizon": "hard",
      "accepted": true,
      "failure_reason": null,
      "realize_attempts": 1,
      "evidence_attempts": 0,
      "elapsed_s": 15.851477653020993,
      "sample_id": "p3-narrow-rsvp-event-001-hard"
    }
  ],
  "failure_reasons": [],
  "timestamp": "2026-04-27T04:13:16.207688+00:00"
}